README.md
setup.py
StableAgents.egg-info/PKG-INFO
StableAgents.egg-info/SOURCES.txt
StableAgents.egg-info/dependency_links.txt
StableAgents.egg-info/top_level.txt
stableagents/__init__.py
stableagents/stableagent.py