Metadata-Version: 2.1
Name: StableAgents
Version: 0.0.1
Summary: Turn LLM's into stable general purpose computer agents
Home-page: https://github.com/light-hq/stableagents.git
Author: Jordan Plows
Classifier: Programming Language :: Python :: 3
Classifier: License :: OSI Approved :: MIT License
Classifier: Operating System :: OS Independent
Requires-Python: >=3.6
